MANIFEST.in
README.rst
setup.py
ox_ebaysdk_settingseditor/__init__.py
ox_ebaysdk_settingseditor/screenshot.png
ox_ebaysdk_settingseditor.egg-info/PKG-INFO
ox_ebaysdk_settingseditor.egg-info/SOURCES.txt
ox_ebaysdk_settingseditor.egg-info/dependency_links.txt
ox_ebaysdk_settingseditor.egg-info/entry_points.txt
ox_ebaysdk_settingseditor.egg-info/requires.txt
ox_ebaysdk_settingseditor.egg-info/top_level.txt
ox_ebaysdk_settingseditor/icons/appointment-soon.png
ox_ebaysdk_settingseditor/icons/face-sad.png
ox_ebaysdk_settingseditor/icons/face-smile.png
ox_ebaysdk_settingseditor/icons/window_icon.png
ox_ebaysdk_settingseditor/templates/api_config.yaml
ox_ebaysdk_settingseditor/tests/__init__.py
ox_ebaysdk_settingseditor/tests/test_setup.py