Metadata-Version: 1.0
Name: ox-ebaysdk-settingseditor
Version: 0.0.3
Summary: gtk editor for ebaysdk configfile (experimental)
Home-page: https://oxidworks.de/
Author: oxidworks
Author-email: apps@oxidworks.de
License: UNKNOWN
Platform: UNKNOWN
